<?xml version="1.0" encoding="utf-8" ?>
<dwsync>
<file name="druid_icon.jpg" server="www.midnightcartel.com/midnightcartel.com/" local="128599774455188050" remote="128599741200000000" />
<file name="hunter_icon.jpg" server="www.midnightcartel.com/midnightcartel.com/" local="128599774455432175" remote="128599741200000000" />
<file name="mage_icon.jpg" server="www.midnightcartel.com/midnightcartel.com/" local="128599774455549355" remote="128599741200000000" />
<file name="paladin_icon.jpg" server="www.midnightcartel.com/midnightcartel.com/" local="128599774455852070" remote="128599741200000000" />
<file name="priest_icon.jpg" server="www.midnightcartel.com/midnightcartel.com/" local="128599774455949720" remote="128599741200000000" />
<file name="rogue_icon.jpg" server="www.midnightcartel.com/midnightcartel.com/" local="128599774456066900" remote="128599741200000000" />
<file name="shaman_icon.jpg" server="www.midnightcartel.com/midnightcartel.com/" local="128599774456174315" remote="128599741200000000" />
<file name="warlock_icon.jpg" server="www.midnightcartel.com/midnightcartel.com/" local="128599774456320790" remote="128599741200000000" />
<file name="warrior_icon.jpg" server="www.midnightcartel.com/midnightcartel.com/" local="128599774456418440" remote="128599741200000000" />
</dwsync>